siggen/__init__.py
siggen/cmd_doc.py
siggen/cmd_fetch_data.py
siggen/cmd_signature.py
siggen/cmd_signify.py
siggen/generator.py
siggen/pipeline.rst
siggen/rules.py
siggen/schema.rst
siggen/siglists_utils.py
siggen/socorro_sha.txt
siggen/utils.py
siggen/siglists/README.rst
siggen/siglists/irrelevant_signature_re.txt
siggen/siglists/prefix_signature_re.txt
siggen/siglists/signature_sentinels.txt
siggen/siglists/signatures_with_line_numbers_re.txt
siggen/siglists/trim_dll_signature_re.txt
siggen/tests/__init__.py
siggen/tests/test_rules.py
siggen/tests/test_siglists.py
siggen/tests/test_signature_generator.py
siggen/tests/test_utils.py
siggen/tests/siglists/test-invalid-sig-list.txt
siggen/tests/siglists/test-sig-list.txt
siggen/tests/siglists/test-valid-sig-list.txt
siggen-2.2.20241029.dist-info/LICENSE
siggen-2.2.20241029.dist-info/METADATA
siggen-2.2.20241029.dist-info/WHEEL
siggen-2.2.20241029.dist-info/entry_points.txt
siggen-2.2.20241029.dist-info/top_level.txt
siggen-2.2.20241029.dist-info/RECORD
