Metadata-Version: 2.1
Name: siggen
Version: 2.2.20241029
Summary: Socorro signature generation extracted as a Python library
Author: Will Kahn-Greene
License: MPLv2
Project-URL: Homepage, https://github.com/willkg/socorro-siggen
Project-URL: Source, https://github.com/willkg/socorro-siggen
Project-URL: Issues, https://github.com/willkg/socorro-siggen
Keywords: socorro
Classifier: Development Status :: 5 - Production/Stable
Classifier: License :: OSI Approved :: Mozilla Public License 2.0 (MPL 2.0)
Classifier: Programming Language :: Python :: 3 :: Only
Classifier: Programming Language :: Python :: 3.9
Classifier: Programming Language :: Python :: 3.10
Classifier: Programming Language :: Python :: 3.11
Classifier: Programming Language :: Python :: 3.12
Classifier: Programming Language :: Python :: 3.13
Classifier: Programming Language :: Python :: Implementation :: CPython
Classifier: Topic :: Software Development :: Libraries :: Python Modules
Requires-Python: >=3.9
License-File: LICENSE
Requires-Dist: glom
Provides-Extra: cli
Requires-Dist: requests <3 ; extra == 'cli'
Provides-Extra: dev
Requires-Dist: build ; extra == 'dev'
Requires-Dist: check-manifest ; extra == 'dev'
Requires-Dist: pytest ; extra == 'dev'
Requires-Dist: requests <3 ; extra == 'dev'
Requires-Dist: ruff ; extra == 'dev'
Requires-Dist: tox ; extra == 'dev'
Requires-Dist: tox-gh-actions ; extra == 'dev'
Requires-Dist: twine ; extra == 'dev'
Requires-Dist: wheel ; extra == 'dev'
